flask_simple_user
