Metadata-Version: 1.0
Name: flask-simple-user
Version: 0.0.9
Summary: flask_user use sqlalchemy.
Home-page: UNKNOWN
Author: UNKNOWN
Author-email: UNKNOWN
License: UNKNOWN
Platform: UNKNOWN
